{
  "version": "8",
  "dialect": "postgres",
  "id": "de609bf0-3886-4b43-b202-6d9ffcc1cf89",
  "prevIds": [
    "49519a9c-f80e-4009-a168-c3bce5c818c4"
  ],
  "ddl": [
    {
      "isRlsEnabled": false,
      "name": "service",
      "entityType": "tables",
      "schema": "public"
    },
    {
      "isRlsEnabled": false,
      "name": "service_check",
      "entityType": "tables",
      "schema": "public"
    },
    {
      "isRlsEnabled": false,
      "name": "session",
      "entityType": "tables",
      "schema": "public"
    },
    {
      "isRlsEnabled": false,
      "name": "user",
      "entityType": "tables",
      "schema": "public"
    },
    {
      "type": "varchar(255)",
      "typeSchema": null,
      "notNull": true,
      "dimensions": 0,
      "default": null,
      "generated": null,
      "identity": null,
      "name": "id",
      "entityType": "columns",
      "schema": "public",
      "table": "service"
    },
    {
      "type": "varchar(255)",
      "typeSchema": null,
      "notNull": true,
      "dimensions": 0,
      "default": null,
      "generated": null,
      "identity": null,
      "name": "user_id",
      "entityType": "columns",
      "schema": "public",
      "table": "service"
    },
    {
      "type": "text",
      "typeSchema": null,
      "notNull": false,
      "dimensions": 0,
      "default": null,
      "generated": null,
      "identity": null,
      "name": "name",
      "entityType": "columns",
      "schema": "public",
      "table": "service"
    },
    {
      "type": "text",
      "typeSchema": null,
      "notNull": true,
      "dimensions": 0,
      "default": null,
      "generated": null,
      "identity": null,
      "name": "url",
      "entityType": "columns",
      "schema": "public",
      "table": "service"
    },
    {
      "type": "integer",
      "typeSchema": null,
      "notNull": true,
      "dimensions": 0,
      "default": "10",
      "generated": null,
      "identity": null,
      "name": "interval_m",
      "entityType": "columns",
      "schema": "public",
      "table": "service"
    },
    {
      "type": "timestamp",
      "typeSchema": null,
      "notNull": true,
      "dimensions": 0,
      "default": "now()",
      "generated": null,
      "identity": null,
      "name": "last_checked",
      "entityType": "columns",
      "schema": "public",
      "table": "service"
    },
    {
      "type": "boolean",
      "typeSchema": null,
      "notNull": false,
      "dimensions": 0,
      "default": null,
      "generated": null,
      "identity": null,
      "name": "is_okay",
      "entityType": "columns",
      "schema": "public",
      "table": "service"
    },
    {
      "type": "varchar(255)",
      "typeSchema": null,
      "notNull": true,
      "dimensions": 0,
      "default": null,
      "generated": null,
      "identity": null,
      "name": "id",
      "entityType": "columns",
      "schema": "public",
      "table": "service_check"
    },
    {
      "type": "varchar(255)",
      "typeSchema": null,
      "notNull": true,
      "dimensions": 0,
      "default": null,
      "generated": null,
      "identity": null,
      "name": "service_id",
      "entityType": "columns",
      "schema": "public",
      "table": "service_check"
    },
    {
      "type": "integer",
      "typeSchema": null,
      "notNull": true,
      "dimensions": 0,
      "default": null,
      "generated": null,
      "identity": null,
      "name": "status",
      "entityType": "columns",
      "schema": "public",
      "table": "service_check"
    },
    {
      "type": "integer",
      "typeSchema": null,
      "notNull": true,
      "dimensions": 0,
      "default": null,
      "generated": null,
      "identity": null,
      "name": "latency_ms",
      "entityType": "columns",
      "schema": "public",
      "table": "service_check"
    },
    {
      "type": "timestamp",
      "typeSchema": null,
      "notNull": false,
      "dimensions": 0,
      "default": "now()",
      "generated": null,
      "identity": null,
      "name": "created_at",
      "entityType": "columns",
      "schema": "public",
      "table": "service_check"
    },
    {
      "type": "varchar(255)",
      "typeSchema": null,
      "notNull": true,
      "dimensions": 0,
      "default": null,
      "generated": null,
      "identity": null,
      "name": "id",
      "entityType": "columns",
      "schema": "public",
      "table": "session"
    },
    {
      "type": "varchar(255)",
      "typeSchema": null,
      "notNull": true,
      "dimensions": 0,
      "default": null,
      "generated": null,
      "identity": null,
      "name": "user_id",
      "entityType": "columns",
      "schema": "public",
      "table": "session"
    },
    {
      "type": "text",
      "typeSchema": null,
      "notNull": true,
      "dimensions": 0,
      "default": null,
      "generated": null,
      "identity": null,
      "name": "token",
      "entityType": "columns",
      "schema": "public",
      "table": "session"
    },
    {
      "type": "timestamp",
      "typeSchema": null,
      "notNull": false,
      "dimensions": 0,
      "default": "now()",
      "generated": null,
      "identity": null,
      "name": "created_at",
      "entityType": "columns",
      "schema": "public",
      "table": "session"
    },
    {
      "type": "timestamp",
      "typeSchema": null,
      "notNull": true,
      "dimensions": 0,
      "default": null,
      "generated": null,
      "identity": null,
      "name": "active_until",
      "entityType": "columns",
      "schema": "public",
      "table": "session"
    },
    {
      "type": "varchar(255)",
      "typeSchema": null,
      "notNull": true,
      "dimensions": 0,
      "default": null,
      "generated": null,
      "identity": null,
      "name": "id",
      "entityType": "columns",
      "schema": "public",
      "table": "user"
    },
    {
      "type": "varchar(255)",
      "typeSchema": null,
      "notNull": true,
      "dimensions": 0,
      "default": null,
      "generated": null,
      "identity": null,
      "name": "name",
      "entityType": "columns",
      "schema": "public",
      "table": "user"
    },
    {
      "type": "text",
      "typeSchema": null,
      "notNull": true,
      "dimensions": 0,
      "default": null,
      "generated": null,
      "identity": null,
      "name": "password",
      "entityType": "columns",
      "schema": "public",
      "table": "user"
    },
    {
      "nameExplicit": false,
      "columns": [
        "user_id"
      ],
      "schemaTo": "public",
      "tableTo": "user",
      "columnsTo": [
        "id"
      ],
      "onUpdate": "NO ACTION",
      "onDelete": "CASCADE",
      "name": "service_user_id_user_id_fkey",
      "entityType": "fks",
      "schema": "public",
      "table": "service"
    },
    {
      "nameExplicit": false,
      "columns": [
        "service_id"
      ],
      "schemaTo": "public",
      "tableTo": "service",
      "columnsTo": [
        "id"
      ],
      "onUpdate": "NO ACTION",
      "onDelete": "CASCADE",
      "name": "service_check_service_id_service_id_fkey",
      "entityType": "fks",
      "schema": "public",
      "table": "service_check"
    },
    {
      "nameExplicit": false,
      "columns": [
        "user_id"
      ],
      "schemaTo": "public",
      "tableTo": "user",
      "columnsTo": [
        "id"
      ],
      "onUpdate": "NO ACTION",
      "onDelete": "CASCADE",
      "name": "session_user_id_user_id_fkey",
      "entityType": "fks",
      "schema": "public",
      "table": "session"
    },
    {
      "columns": [
        "id"
      ],
      "nameExplicit": false,
      "name": "service_pkey",
      "schema": "public",
      "table": "service",
      "entityType": "pks"
    },
    {
      "columns": [
        "id"
      ],
      "nameExplicit": false,
      "name": "service_check_pkey",
      "schema": "public",
      "table": "service_check",
      "entityType": "pks"
    },
    {
      "columns": [
        "id"
      ],
      "nameExplicit": false,
      "name": "session_pkey",
      "schema": "public",
      "table": "session",
      "entityType": "pks"
    },
    {
      "columns": [
        "id"
      ],
      "nameExplicit": false,
      "name": "user_pkey",
      "schema": "public",
      "table": "user",
      "entityType": "pks"
    },
    {
      "nameExplicit": false,
      "columns": [
        "name"
      ],
      "nullsNotDistinct": false,
      "name": "user_name_key",
      "schema": "public",
      "table": "user",
      "entityType": "uniques"
    }
  ],
  "renames": []
}